cadquery_massembly/__init__.py
cadquery_massembly/_version.py
cadquery_massembly/cq_editor.py
cadquery_massembly/massembly.py
cadquery_massembly/mate.py
cadquery_massembly-0.9.0.dist-info/METADATA
cadquery_massembly-0.9.0.dist-info/WHEEL
cadquery_massembly-0.9.0.dist-info/top_level.txt
cadquery_massembly-0.9.0.dist-info/RECORD
